libheap/UF.py
libheap/__init__.py
libheap/libheap.py
libheap-0.5.dist-info/LICENSE
libheap-0.5.dist-info/METADATA
libheap-0.5.dist-info/WHEEL
libheap-0.5.dist-info/top_level.txt
libheap-0.5.dist-info/RECORD
