Metadata-Version: 2.1
Name: libheap
Version: 0.5
Summary: a general heap library
Home-page: https://github.com/yutao-li/libheap
Author: masterlee
Author-email: 870070392@qq.com
License: MIT
Download-URL: https://github.com/yutao-li/libheap/archive/0.5.tar.gz
Platform: UNKNOWN
Classifier: Development Status :: 3 - Alpha
Classifier: License :: OSI Approved :: MIT License
Classifier: Programming Language :: Python :: 3
